{"type":"FeatureCollection","features":[{"type":"Feature","id":2,"geometry":{"type":"Point","coordinates":[10.009274279090691,36.895551069000419]},"properties":{"OBJECTID":2,"Entity":"Point","Handle":"369","Layer":"IF","LyrFrzn":0,"LyrLock":0,"LyrOn":1,"LyrVPFrzn":0,"LyrHandle":"347","Color":7,"EntColor":7,"LyrColor":7,"BlkColor":0,"Linetype":"BYBLOCK","EntLinetype":"Continuous","LyrLnType":"Continuous","BlkLinetype":"","Elevation":0,"Thickness":0,"LineWt":90,"EntLineWt":90,"LyrLineWt":-3,"BlkLineWt":-1,"RefName":"","LTScale":1,"Angle":0,"ExtX":0,"ExtY":0,"ExtZ":1,"DocName":"Intermediate Approach.dwg","DocPath":"C:\\Data_DNA\\Cad_Layers\\Intermediate Approach.dwg","DocType":"DWG","DocVer":"AC1032","DocUpdate":1743307394000,"DocId":248434296145367328,"ScaleX":1,"ScaleY":1,"ScaleZ":1}},{"type":"Feature","id":3,"geometry":{"type":"Point","coordinates":[9.9844090711173923,36.814510621385921]},"properties":{"OBJECTID":3,"Entity":"Point","Handle":"36A","Layer":"IF","LyrFrzn":0,"LyrLock":0,"LyrOn":1,"LyrVPFrzn":0,"LyrHandle":"347","Color":5,"EntColor":5,"LyrColor":7,"BlkColor":0,"Linetype":"BYBLOCK","EntLinetype":"Continuous","LyrLnType":"Continuous","BlkLinetype":"","Elevation":0,"Thickness":0,"LineWt":90,"EntLineWt":90,"LyrLineWt":-3,"BlkLineWt":-1,"RefName":"","LTScale":1,"Angle":0,"ExtX":0,"ExtY":0,"ExtZ":1,"DocName":"Intermediate Approach.dwg","DocPath":"C:\\Data_DNA\\Cad_Layers\\Intermediate Approach.dwg","DocType":"DWG","DocVer":"AC1032","DocUpdate":1743307394000,"DocId":248434296145367328,"ScaleX":1,"ScaleY":1,"ScaleZ":1}},{"type":"Feature","id":4,"geometry":{"type":"Point","coordinates":[10.034194017290455,36.976584413482634]},"properties":{"OBJECTID":4,"Entity":"Point","Handle":"36B","Layer":"IF","LyrFrzn":0,"LyrLock":0,"LyrOn":1,"LyrVPFrzn":0,"LyrHandle":"347","Color":5,"EntColor":5,"LyrColor":7,"BlkColor":0,"Linetype":"BYBLOCK","EntLinetype":"Continuous","LyrLnType":"Continuous","BlkLinetype":"","Elevation":0,"Thickness":0,"LineWt":90,"EntLineWt":90,"LyrLineWt":-3,"BlkLineWt":-1,"RefName":"","LTScale":1,"Angle":0,"ExtX":0,"ExtY":0,"ExtZ":1,"DocName":"Intermediate Approach.dwg","DocPath":"C:\\Data_DNA\\Cad_Layers\\Intermediate Approach.dwg","DocType":"DWG","DocVer":"AC1032","DocUpdate":1743307394000,"DocId":248434296145367328,"ScaleX":1,"ScaleY":1,"ScaleZ":1}},{"type":"Feature","id":5,"geometry":{"type":"Point","coordinates":[9.9968348958021167,36.85503178861795]},"properties":{"OBJECTID":5,"Entity":"Point","Handle":"36C","Layer":"IF","LyrFrzn":0,"LyrLock":0,"LyrOn":1,"LyrVPFrzn":0,"LyrHandle":"347","Color":172,"EntColor":172,"LyrColor":7,"BlkColor":0,"Linetype":"BYBLOCK","EntLinetype":"Continuous","LyrLnType":"Continuous","BlkLinetype":"","Elevation":0,"Thickness":0,"LineWt":90,"EntLineWt":90,"LyrLineWt":-3,"BlkLineWt":-1,"RefName":"","LTScale":1,"Angle":0,"ExtX":0,"ExtY":0,"ExtZ":1,"DocName":"Intermediate Approach.dwg","DocPath":"C:\\Data_DNA\\Cad_Layers\\Intermediate Approach.dwg","DocType":"DWG","DocVer":"AC1032","DocUpdate":1743307394000,"DocId":248434296145367328,"ScaleX":1,"ScaleY":1,"ScaleZ":1}},{"type":"Feature","id":6,"geometry":{"type":"Point","coordinates":[10.021727311652747,36.936068632055182]},"properties":{"OBJECTID":6,"Entity":"Point","Handle":"36D","Layer":"IF","LyrFrzn":0,"LyrLock":0,"LyrOn":1,"LyrVPFrzn":0,"LyrHandle":"347","Color":172,"EntColor":172,"LyrColor":7,"BlkColor":0,"Linetype":"BYBLOCK","EntLinetype":"Continuous","LyrLnType":"Continuous","BlkLinetype":"","Elevation":0,"Thickness":0,"LineWt":90,"EntLineWt":90,"LyrLineWt":-3,"BlkLineWt":-1,"RefName":"","LTScale":1,"Angle":0,"ExtX":0,"ExtY":0,"ExtZ":1,"DocName":"Intermediate Approach.dwg","DocPath":"C:\\Data_DNA\\Cad_Layers\\Intermediate Approach.dwg","DocType":"DWG","DocVer":"AC1032","DocUpdate":1743307394000,"DocId":248434296145367328,"ScaleX":1,"ScaleY":1,"ScaleZ":1}}]}